llm_safeguard-0.1.0.dist-info/licenses/LICENSE
safeguarding/__init__.py
safeguarding/log_viewer.py
safeguarding/run_microservice.py
safeguarding/api/__init__.py
safeguarding/api/api_service.py
safeguarding/config/__init__.py
safeguarding/config/safeguard_config.json
safeguarding/core/__init__.py
safeguarding/core/classifier_filter.py
safeguarding/core/keyword_filter.py
safeguarding/core/models.py
safeguarding/core/orchestrator.py
safeguarding/core/perspective_api_filter.py
safeguarding/filters/__init__.py
safeguarding/filters/pipeline.py
safeguarding/hooks/__init__.py
safeguarding/hooks/post_process_hook.py
safeguarding/hooks/pre_process_hook.py
safeguarding/middleware/__init__.py
safeguarding/middleware/base.py
safeguarding/middleware/django_adapter.py
safeguarding/middleware/fastapi_adapter.py
safeguarding/middleware/flask_adapter.py
safeguarding/utils/__init__.py
safeguarding/utils/anonymizer.py
safeguarding/utils/config_loader.py
safeguarding/utils/logger.py
safeguarding/utils/override_checker.py
llm_safeguard-0.1.0.dist-info/METADATA
llm_safeguard-0.1.0.dist-info/WHEEL
llm_safeguard-0.1.0.dist-info/top_level.txt
llm_safeguard-0.1.0.dist-info/RECORD
