Metadata-Version: 2.4
Name: LLM-safeguard
Version: 0.1.0
Summary: Universal middleware for safeguarding AI‑generated content
Author-email: Julius Deane <founder.haail@gmail.com>
License: MIT
Keywords: content-moderation,safety,middleware,LLM
Classifier: Programming Language :: Python :: 3
Classifier: License :: OSI Approved :: MIT License
Classifier: Operating System :: OS Independent
Requires-Python: >=3.10
License-File: LICENSE
Requires-Dist: fastapi>=0.95.0
Requires-Dist: transformers>=4.30.0
Requires-Dist: requests>=2.25.0
Requires-Dist: torch
Requires-Dist: uvicorn[standard]
Provides-Extra: flask
Requires-Dist: flask>=2.0.0; extra == "flask"
Provides-Extra: django
Requires-Dist: django>=3.2; extra == "django"
Provides-Extra: streamlit
Requires-Dist: streamlit; extra == "streamlit"
Provides-Extra: dev
Requires-Dist: pytest; extra == "dev"
Requires-Dist: httpx; extra == "dev"
Requires-Dist: black; extra == "dev"
Requires-Dist: isort; extra == "dev"
Dynamic: license-file
